README.txt
setup.cfg
setup.py
TGFKLookup.egg-info/PKG-INFO
TGFKLookup.egg-info/SOURCES.txt
TGFKLookup.egg-info/dependency_links.txt
TGFKLookup.egg-info/entry_points.txt
TGFKLookup.egg-info/not-zip-safe
TGFKLookup.egg-info/paster_plugins.txt
TGFKLookup.egg-info/requires.txt
TGFKLookup.egg-info/sqlobject.txt
TGFKLookup.egg-info/top_level.txt
tgfklookup/__init__.py
tgfklookup/release.py
tgfklookup/widgets.py
tgfklookup/static/css/autocompletefield.css
tgfklookup/static/images/favicon.ico
tgfklookup/static/images/spinner.gif
tgfklookup/static/images/tg_under_the_hood.png
tgfklookup/static/images/under_the_hood_blue.png
tgfklookup/static/javascript/Copy of autocompletingfklookup.js
tgfklookup/static/javascript/autocompletingfklookup.js
tgfklookup/templates/__init__.py
